spio/__init__.py
spio/compiler/__init__.py
spio/compiler/arch.py
spio/compiler/compile.py
spio/compiler/compile_kernel.py
spio/compiler/compile_nvcc.py
spio/compiler/compiler_pool.py
spio/compiler/cuda_paths.py
spio/compiler/disasm.py
spio/compiler/flags.py
spio/cuda/__init__.py
spio/cuda/cdriver.pxd
spio/cuda/driver.cpython-39-x86_64-linux-gnu.so
spio/cuda/driver.pyi
spio/cuda/driver.pyx
spio/cuda/nvrtc_ctypes.py
spio/functional/__init__.py
spio/functional/conv2d_gw8_function.py
spio/generators/__init__.py
spio/generators/async_strip_loader.py
spio/generators/built_in.py
spio/generators/checkerboard.py
spio/generators/compound_index.py
spio/generators/coordinates.py
spio/generators/data_type.py
spio/generators/derived_dimension.py
spio/generators/dim.py
spio/generators/dims.py
spio/generators/fold.py
spio/generators/fragment.py
spio/generators/fragment_index.py
spio/generators/fragment_type.py
spio/generators/gen_specs.py
spio/generators/generators.py
spio/generators/generators_class.py
spio/generators/macros.py
spio/generators/matmul.py
spio/generators/params.py
spio/generators/tensor.py
spio/include/__init__.py
spio/include/spio.cuh
spio/include/spio/__init__.py
spio/include/spio/allocator.h
spio/include/spio/async_strip_loader.cuh
spio/include/spio/checkerboard_index.h
spio/include/spio/compound_index.h
spio/include/spio/compound_index_base.h
spio/include/spio/coordinates.h
spio/include/spio/dim.h
spio/include/spio/dim_info.h
spio/include/spio/fifo.cuh
spio/include/spio/fragment.cuh
spio/include/spio/fragment_index.h
spio/include/spio/fragment_load_index.h
spio/include/spio/fragment_mma.cuh
spio/include/spio/ldmatrix.cuh
spio/include/spio/macros.h
spio/include/spio/mathutil.h
spio/include/spio/memory.cuh
spio/include/spio/meta.h
spio/include/spio/mma.cuh
spio/include/spio/pipeline.h
spio/include/spio/semaphore.cuh
spio/include/spio/strip_loader_params.h
spio/include/spio/tensor.h
spio-0.8.0.dist-info/METADATA
spio-0.8.0.dist-info/WHEEL
spio-0.8.0.dist-info/top_level.txt
spio-0.8.0.dist-info/RECORD
spio-0.8.0.dist-info/licenses/LICENSE
