Metadata-Version: 2.4
Name: spio
Version: 0.8.0
Summary: Experimental CUDA kernel framework unifying typed dimensions, NVRTC JIT specialization, and ML‑guided tuning.
Author-email: Andrew Lavin <alavin@acm.org>
Project-URL: Homepage, https://github.com/andravin/spio
Project-URL: Issues, https://github.com/andravin/spio/issues
Classifier: Programming Language :: Python :: 3 :: Only
Classifier: Programming Language :: Python :: 3.9
Classifier: Programming Language :: Python :: 3.10
Classifier: Programming Language :: Python :: 3.11
Classifier: Programming Language :: Python :: 3.12
Classifier: License :: OSI Approved :: Apache Software License
Classifier: Operating System :: POSIX :: Linux
Requires-Python: >=3.9
License-File: LICENSE
Requires-Dist: torch>=2.4.0
Requires-Dist: pytest
Requires-Dist: xgboost
Requires-Dist: appdirs
Requires-Dist: requests
Requires-Dist: filelock
Requires-Dist: packaging
Requires-Dist: importlib_resources>=6.0.0
Dynamic: license-file
